{
    "display": {
        "icon": {
            "item": "minecraft:end_portal_frame"
        },
        "title": {
            "translate": "advancement.alternative_ending"
        },
        "description": {
            "translate": "advancement.alternative_ending.desc"
        }
    },
    "parent": "farlanders:kill_classic_enderman",
    "criteria": {
        "frame": {
          "trigger": "minecraft:inventory_changed",
          "conditions": {
            "items": [
              {
                "item": "minecraft:end_portal_frame"
              }
            ]
          }
        }
  },
  "requirements": [
    [
      "frame"
    ]
  ]
}